AUTHORS
mapping.py
pflexcy.c
pflexible.py
setup.cfg
setup.py
f2py_build/FortFlex.f
f2py_build/README
f2py_build/build_FortFlex.sh
pflexible.egg-info/PKG-INFO
pflexible.egg-info/SOURCES.txt
pflexible.egg-info/dependency_links.txt
pflexible.egg-info/top_level.txt