Metadata-Version: 1.0
Name: pflexible
Version: 0.9.1
Summary: A Python interface to FLEXPART data.
Home-page: http://bitbucket.com/jfburkhart/pflexible
Author: John F. Burkhart
Author-email: jfburkhart@gmail.com
License: Creative Commons
Platform: UNKNOWN
